dbestclient/__init__.py
dbestclient/main.py
dbestclient/catalog/__init__.py
dbestclient/catalog/catalog.py
dbestclient/cli/__init__.py
dbestclient/cli/prompt.py
dbestclient/executor/__init__.py
dbestclient/executor/executor.py
dbestclient/executor/queryengine.py
dbestclient/executor/queryengineft.py
dbestclient/executor/queryenginemdn.py
dbestclient/executor/test.py
dbestclient/io/__init__.py
dbestclient/io/file.py
dbestclient/io/filereader.py
dbestclient/io/getxy.py
dbestclient/io/reservoir.py
dbestclient/io/sampling.py
dbestclient/io/stratifiedreservoir.py
dbestclient/ml/__init__.py
dbestclient/ml/density.py
dbestclient/ml/embedding.py
dbestclient/ml/ft.py
dbestclient/ml/integral.py
dbestclient/ml/mdn.py
dbestclient/ml/modeltrainer.py
dbestclient/ml/modelwraper.py
dbestclient/ml/regression.py
dbestclient/ml/wordembedding.py
dbestclient/parser/__init__.py
dbestclient/parser/parser.py
dbestclient/socket/__init__.py
dbestclient/socket/app_client.py
dbestclient/socket/app_server.py
dbestclient/socket/libclient.py
dbestclient/socket/libserver.py
dbestclient/tools/__init__.py
dbestclient/tools/date.py
dbestclient/tools/dftools.py
dbestclient/tools/running_parameters.py
dbestclient/tools/variables.py
tests/integration/__init__.py
tests/integration/dbestclient/__init__.py
tests/integration/dbestclient/executor/__init__.py
tests/integration/dbestclient/executor/test_executor.py
tests/unit/__init__.py
tests/unit/dbestclient/__init__.py
tests/unit/dbestclient/io/__init__.py
tests/unit/dbestclient/io/test_stratifiedreservoir.py
tests/unit/dbestclient/ml/__init__.py
tests/unit/dbestclient/ml/test_test.py
tests/unit/dbestclient/ml/test_word_embedding.py
tests/unit/dbestclient/parser/__init__.py
tests/unit/dbestclient/parser/test_parser.py
dbestclient-3.0.dist-info/LICENSE
dbestclient-3.0.dist-info/METADATA
dbestclient-3.0.dist-info/WHEEL
dbestclient-3.0.dist-info/entry_points.txt
dbestclient-3.0.dist-info/top_level.txt
dbestclient-3.0.dist-info/RECORD
